{"organizations": [], "uuid": "d68f719d07ca34de9a1deca88a24a8783867f5de", "thread": {"social": {"gplus": {"shares": 0}, "pinterest": {"shares": 0}, "vk": {"shares": 0}, "linkedin": {"shares": 0}, "facebook": {"likes": 367, "shares": 367, "comments": 0}, "stumbledupon": {"shares": 0}}, "site_full": "www.huffingtonpost.com", "main_image": "http://img.huffingtonpost.com/asset/2000_1000/58a330472900002200f2654a.png?cache=r0vodjeltl", "site_section": "http://www.huffingtonpost.com//feeds/index.xml", "section_title": "The Huffington Post | The Full Feed", "url": "http://www.huffingtonpost.com/entry/laverne-cox-meets-beyonce_us_58a32fbee4b03df370da7ff2", "country": "US", "domain_rank": 139, "title": "Laverne Cox Finally Met Beyoncé And Reacted Like Any Human Would, Really", "performance_score": 3, "site": "huffingtonpost.com", "participants_count": 1, "title_full": "Laverne Cox Finally Met Beyoncé And Reacted Like Any Human Would, Really", "spam_score": 0.0, "site_type": "news", "published": "2017-02-15T00:13:00.000+02:00", "replies_count": 0, "uuid": "d68f719d07ca34de9a1deca88a24a8783867f5de"}, "author": "JamesMichael Nichols", "url": "http://www.huffingtonpost.com/entry/laverne-cox-meets-beyonce_us_58a32fbee4b03df370da7ff2", "ord_in_thread": 0, "title": "Laverne Cox Finally Met Beyoncé And Reacted Like Any Human Would, Really", "locations": [], "entities": {"persons": [{"name": "laverne cox", "sentiment": "negative"}, {"name": "gavin grimm", "sentiment": "none"}, {"name": "beyoncé", "sentiment": "none"}, {"name": "laverne", "sentiment": "none"}, {"name": "cox", "sentiment": "none"}, {"name": "metallica", "sentiment": "none"}, {"name": "jamesmichael nichols", "sentiment": "none"}, {"name": "lady gaga", "sentiment": "none"}], "locations": [], "organizations": [{"name": "pst  cox", "sentiment": "none"}]}, "highlightText": "", "language": "english", "persons": [], "text": "Laverne Cox Finally Met Beyoncé And Reacted Like Any Human Would, Really ❤️️ ❤️️ ❤️️ 02/14/2017 12:13 pm ET JamesMichael Nichols Queer Voices Deputy Editor, The Huffington Post \nTalk about a long time coming! Actress and transgender activist Laverne Cox finally met her idol, Beyoncé. \nCox has been pretty upfront about her stanning for Queen B over the years, even paying tribute to the artist by recreating her iconic “Single Ladies” look in Cosmopolitan. (She also lost her mind when Beyoncé sent her a holiday card and sweatshirt in 2014.) At the 2017 Grammy’s on Sunday, the pair finally met face to face and Cox was ecstatic. A post shared by laverne cox (@lavernecox) on Feb 12, 2017 at 10:14pm PST A post shared by laverne cox (@lavernecox) on Feb 13, 2017 at 12:46pm PST \nCox introduced Lady Gaga and Metallica at the Grammy’s Sunday night, using her time on stage to draw attention to the upcoming transgender rights SCOTUS case surrounding Gavin Grimm. \nWe couldn’t be happier for you, Laverne!! More:", "external_links": [], "published": "2017-02-15T00:13:00.000+02:00", "crawled": "2017-02-14T19:19:48.399+02:00", "highlightTitle": ""}