{"organizations": [], "uuid": "360e344ea6a33856eeed3fb469580945a211cf49", "thread": {"social": {"gplus": {"shares": 0}, "pinterest": {"shares": 0}, "vk": {"shares": 0}, "linkedin": {"shares": 0}, "facebook": {"likes": 347, "shares": 347, "comments": 0}, "stumbledupon": {"shares": 0}}, "site_full": "www.givemesport.com", "main_image": "http://givemesport.azureedge.net/images/17/02/12/5c71c8dd33ecdf6175f182400e3e337f/1200.jpg", "site_section": "", "section_title": "", "url": "http://www.givemesport.com/984580-cody-rhodes-accidentally-hits-finishing-move-on-his-wife-during-match", "country": "US", "domain_rank": 1212, "title": "Cody Rhodes accidentally hits finishing move on his wife during match | GiveMeSport", "performance_score": 3, "site": "givemesport.com", "participants_count": 0, "title_full": "Cody Rhodes accidentally hits finishing move on his wife during match | GiveMeSport", "spam_score": 0.053, "site_type": "news", "published": "2017-02-13T03:44:00.000+02:00", "replies_count": 0, "uuid": "360e344ea6a33856eeed3fb469580945a211cf49"}, "author": "", "url": "http://www.givemesport.com/984580-cody-rhodes-accidentally-hits-finishing-move-on-his-wife-during-match", "ord_in_thread": 0, "title": "Cody Rhodes accidentally hits finishing move on his wife during match | GiveMeSport", "locations": [], "entities": {"persons": [{"name": "cody rhodes", "sentiment": "negative"}, {"name": "givemesport cody rhodes", "sentiment": "negative"}, {"name": "cody", "sentiment": "negative"}, {"name": "brandi", "sentiment": "none"}, {"name": "rhodes", "sentiment": "none"}, {"name": "cross rhodes", "sentiment": "none"}], "locations": [{"name": "wrestle kingdom", "sentiment": "none"}], "organizations": [{"name": "bullet club", "sentiment": "none"}]}, "highlightText": "", "language": "english", "persons": [], "text": "Cody Rhodes accidentally hits finishing move on his wife during match Published 24/7 \nAlthough Cody Rhodes is no longer with the WWE, he’s done a brilliant job of ensuring he’s a name fans still talk about while on the independent scene. \nHe’s already competed at WrestleMania, he picked up a win at Wrestle Kingdom 11 this year, he’s a member of The Bullet Club – and his stock just continues to increase. INDIE SUCCESS \nCompanies now bring him in as a star attraction, and rightfully so as he very rarely disappoints. SIGN UP NOW \nWant to become a GMS writer? Sign up now and submit a 250-word test article: http://gms.to/haveyoursay4 Article continues below \nA trend has emerged with The American Nightmare, as his antics have started to go viral this year. \nHe followed that up with another brutal moment , where Rhodes landed a vicious chair shot to the head of this opponent. \nHowever, the most recent clip is perhaps the best one yet. CROSS RHODES ON HIS WIFE \nBrandi – the wife of Cody – followed in his footsteps by asking for her WWE release, and the two are now seen together in every promotion they’re booked for, and she was involved in a brilliant spot at a WrestlePro show recently. \nAs you’ll be able to see in her Instagram post below, Rhodes was ‘blinded’ for a brief moment because of his opponents underhanded tactics. \nAs she got into the ring to confront his opponent, the former Intercontinental Champion accidentally hit a Cross Rhodes on his wife, thinking it was the opponent – and she took it like a pro. \nIt’s great to see Cody having fun on the independent scene, one of the many reasons he left the WWE in the first place. \nWhat did you make of the Cross Rhodes he hit on his wife? Have YOUR say in the comments section below. \nDo YOU want to write for GiveMeSport? Get started today by signing-up and submitting an article HERE: http://gms.to/writeforgms Topics: ", "external_links": [], "published": "2017-02-13T03:44:00.000+02:00", "crawled": "2017-02-13T09:34:29.060+02:00", "highlightTitle": ""}