{"organizations": [], "uuid": "508cf1603265ffd4279087b340a7a2b56a23895d", "thread": {"social": {"gplus": {"shares": 0}, "pinterest": {"shares": 0}, "vk": {"shares": 0}, "linkedin": {"shares": 0}, "facebook": {"likes": 176, "shares": 176, "comments": 1}, "stumbledupon": {"shares": 0}}, "site_full": "globalnews.ca", "main_image": "https://shawglobalnews.files.wordpress.com/2017/02/tyrone-tootoosis-poundmaker-first-nation-facebook.jpg?quality=70&strip=all&w=720&h=480&crop=1", "site_section": "", "section_title": "", "url": "http://globalnews.ca/news/3245751/first-nations-advocate-tyrone-tootoosis-passes-away/", "country": "US", "domain_rank": 6425, "title": "First Nations advocate Tyrone Tootoosis passes away - Saskatoon | Globalnews.ca", "performance_score": 1, "site": "globalnews.ca", "participants_count": 0, "title_full": "First Nations advocate Tyrone Tootoosis passes away - Saskatoon | Globalnews.ca", "spam_score": 0.004, "site_type": "news", "published": "2017-02-13T18:29:00.000+02:00", "replies_count": 0, "uuid": "508cf1603265ffd4279087b340a7a2b56a23895d"}, "author": "David Giles", "url": "http://globalnews.ca/news/3245751/first-nations-advocate-tyrone-tootoosis-passes-away/", "ord_in_thread": 0, "title": "First Nations advocate Tyrone Tootoosis passes away - Saskatoon | Globalnews.ca", "locations": [], "entities": {"persons": [], "locations": [], "organizations": []}, "highlightText": "", "language": "english", "persons": [], "text": "February 13, 2017 11:29 am First Nations advocate Tyrone Tootoosis passes away By David Giles Senior Web Producer Global News \nWell known First Nations advocate Tyrone Tootoosis has passed away at the age of 58. Facebook What is this? \nSponsored content is written by Global News' editorial staff without any editorial influence by the sponsor. If you'd like to learn more... X What is this? \nSponsored content is written by Global News' without any editorial influence by the sponsor. If you'd like to learn more... - \nTyrone Tootoosis, a well-known First Nations advocate, has passed away. \nTootoosis, 58, died Sunday morning. \n“Tyrone left us early this morning, riding a comet during the full moon snow,” states a post on his Facebook page. \nTootoosis was a recognized leader in the province, who spent years sharing his culture with others. \nHe was also an artist and an actor. He was the voice of Uncle Peter and Mr. Thunderbird on Wapos Bay: The Series and played Chief Poundmaker, his great-great-granduncle in the TV mini-series Big Bear . \nA service has been scheduled for Wednesday morning at Poundmaker First Nation Veterans Hall. Related ", "external_links": [], "published": "2017-02-13T18:29:00.000+02:00", "crawled": "2017-02-14T01:31:11.341+02:00", "highlightTitle": ""}