{"organizations": [], "uuid": "8d93b9014aac0a72a0dce0e170b693ecc222497b", "thread": {"social": {"gplus": {"shares": 0}, "pinterest": {"shares": 0}, "vk": {"shares": 0}, "linkedin": {"shares": 0}, "facebook": {"likes": 122, "shares": 122, "comments": 0}, "stumbledupon": {"shares": 0}}, "site_full": "www.malaysiakini.com", "main_image": "http://mk-cdn.mkini.net/1085/f5b3ff558b985743fdcef4e6f4c8789c.jpg", "site_section": "", "section_title": "", "url": "https://www.malaysiakini.com/news/373920", "country": "US", "domain_rank": 5504, "title": "调查显示西蒂知情下犯案\n总警长驳斥“中圈套”说法 《当今大马》", "performance_score": 1, "site": "malaysiakini.com", "participants_count": 0, "title_full": "调查显示西蒂知情下犯案\n总警长驳斥“中圈套”说法 《当今大马》", "spam_score": 0.001, "site_type": "news", "published": "2017-02-28T00:58:00.000+02:00", "replies_count": 0, "uuid": "8d93b9014aac0a72a0dce0e170b693ecc222497b"}, "author": "", "url": "https://www.malaysiakini.com/news/373920", "ord_in_thread": 0, "title": "调查显示西蒂知情下犯案\n总警长驳斥“中圈套”说法 《当今大马》", "locations": [], "entities": {"persons": [], "locations": [], "organizations": []}, "highlightText": "", "language": "english", "persons": [], "text": "", "external_links": [], "published": "2017-02-28T00:58:00.000+02:00", "crawled": "2017-02-27T15:26:12.355+02:00", "highlightTitle": ""}